pyspacegdn/response.py
pyspacegdn/__init__.py
pyspacegdn/spacegdn.py
pyspacegdn/requests/find_request.py
pyspacegdn/requests/__init__.py
pyspacegdn/requests/request.py
pySpaceGDN-2.0.1.dist-info/top_level.txt
pySpaceGDN-2.0.1.dist-info/WHEEL
pySpaceGDN-2.0.1.dist-info/DESCRIPTION.rst
pySpaceGDN-2.0.1.dist-info/metadata.json
pySpaceGDN-2.0.1.dist-info/RECORD
pySpaceGDN-2.0.1.dist-info/METADATA
