Metadata-Version: 2.0
Name: pySpaceGDN
Version: 2.0.1
Summary: Python Module for the SpaceGDN JSON API
Home-page: https://github.com/totokaka/pySpaceGDN
Author: Tobias Laundal
Author-email: mail+pyspacegdn@totokaka.io
License: MIT
Keywords: SpaceGDN pySpaceGDN SpaceCP GDN
Platform: UNKNOWN
Classifier: Development Status :: 4 - Beta
Classifier: Intended Audience :: Developers
Classifier: Natural Language :: English
Classifier: License :: OSI Approved :: MIT License
Classifier: Operating System :: OS Independent
Classifier: Programming Language :: Python :: 3
Classifier: Topic :: Software Development :: Libraries :: Application Frameworks
Requires-Dist: requests
